whatsappchatbot/__init__.py
whatsappchatbot/extract_chats.py
whatsappchatbot/response.py
whatsappchatbot/selenium_automation.py
whatsappchatbot/whatsappChatbot.py
whatsappchatbot_pkg_seemantsingh-0.0.2.dist-info/LICENSE
whatsappchatbot_pkg_seemantsingh-0.0.2.dist-info/METADATA
whatsappchatbot_pkg_seemantsingh-0.0.2.dist-info/WHEEL
whatsappchatbot_pkg_seemantsingh-0.0.2.dist-info/top_level.txt
whatsappchatbot_pkg_seemantsingh-0.0.2.dist-info/RECORD
