Metadata-Version: 2.1
Name: whatsappchatbot-pkg-seemantsingh
Version: 0.0.2
Summary: Whatsapp chatbot
Home-page: https://github.com/maxsanwal/whatsappChatbot
Author: Seemant Singh
Author-email: seemantskype@gmail.com
License: UNKNOWN
Project-URL: Bug Tracker, https://github.com/maxsanwal/whatsappChatbot/issues
Platform: UNKNOWN
Classifier: Programming Language :: Python :: 3
Classifier: License :: OSI Approved :: MIT License
Classifier: Operating System :: OS Independent
Requires-Python: >=3.6
